random_root_locus_generator/__init__.py
random_root_locus_generator-1.0.6.dist-info/METADATA
random_root_locus_generator-1.0.6.dist-info/WHEEL
random_root_locus_generator-1.0.6.dist-info/top_level.txt
random_root_locus_generator-1.0.6.dist-info/RECORD
