Metadata-Version: 2.1
Name: random-root-locus-generator
Version: 1.0.6
Summary: package for generating random root locus problems intelligently
Home-page: https://github.com/ryanGT/random_root_locus_generator
Author: Ryan Krauss
Author-email: ryanwkrauss@gmail.com
License: UNKNOWN
Platform: UNKNOWN
Classifier: Programming Language :: Python :: 3
Classifier: License :: OSI Approved :: MIT License
Classifier: Operating System :: OS Independent
